icemac.addressbook-9.4-py3.7-nspkg.pth
icemac/addressbook/__init__.py
icemac/addressbook/adapter.py
icemac/addressbook/address.py
icemac/addressbook/addressbook.py
icemac/addressbook/application.zcml
icemac/addressbook/classes.zcml
icemac/addressbook/configure.zcml
icemac/addressbook/conftest.py
icemac/addressbook/entities.py
icemac/addressbook/fieldsource.py
icemac/addressbook/fixtures.py
icemac/addressbook/ftesting-base.zcml
icemac/addressbook/ftesting.zcml
icemac/addressbook/i18n.py
icemac/addressbook/icalendar.py
icemac/addressbook/interfaces.py
icemac/addressbook/keyword.py
icemac/addressbook/orderstorage.py
icemac/addressbook/overrides.zcml
icemac/addressbook/patch.py
icemac/addressbook/permissions.zcml
icemac/addressbook/person.py
icemac/addressbook/roles.zcml
icemac/addressbook/sources.py
icemac/addressbook/startup.py
icemac/addressbook/testing.py
icemac/addressbook/translationtesting.zcml
icemac/addressbook/utils.py
icemac/addressbook/browser/__init__.py
icemac/addressbook/browser/base.py
icemac/addressbook/browser/breadcrumb.pt
icemac/addressbook/browser/breadcrumb.py
icemac/addressbook/browser/bullet-menu.pt
icemac/addressbook/browser/configure.zcml
icemac/addressbook/browser/conftest.py
icemac/addressbook/browser/cookieconsent.py
icemac/addressbook/browser/datamanager.py
icemac/addressbook/browser/datetime_input.pt
icemac/addressbook/browser/errormessage.py
icemac/addressbook/browser/favicon.py
icemac/addressbook/browser/form.pt
icemac/addressbook/browser/form.py
icemac/addressbook/browser/imageselect_input.pt
icemac/addressbook/browser/inspector.pt
icemac/addressbook/browser/inspector.py
icemac/addressbook/browser/interfaces.py
icemac/addressbook/browser/layout.pt
icemac/addressbook/browser/layout.py
icemac/addressbook/browser/list_select2_input.pt
icemac/addressbook/browser/metadata.py
icemac/addressbook/browser/namespace.py
icemac/addressbook/browser/personlist.py
icemac/addressbook/browser/resource.py
icemac/addressbook/browser/table.py
icemac.addressbook-9.4.dist-info/LICENSE.TXT
icemac.addressbook-9.4.dist-info/METADATA
icemac.addressbook-9.4.dist-info/WHEEL
icemac.addressbook-9.4.dist-info/entry_points.txt
icemac.addressbook-9.4.dist-info/namespace_packages.txt
icemac.addressbook-9.4.dist-info/top_level.txt
icemac.addressbook-9.4.dist-info/RECORD
