Metadata-Version: 2.1
Name: icemac.addressbook
Version: 9.4
Summary: Multi user address book application
Home-page: https://github.com/icemac/icemac.addressbook
Author: Michael Howitz
Author-email: icemac@gmx.net
License: MIT
Download-URL: https://pypi.org/project/icemac.addressbook
Project-URL: Documentation, https://icemacaddressbook.readthedocs.io
Project-URL: Source, https://github.com/icemac/icemac.addressbook
Project-URL: Tracker, https://github.com/icemac/icemac.addressbook/issues
Keywords: python address book addressbook zope3 zope application web phone number e-mail email home page homepage wsgi
Platform: UNKNOWN
Classifier: Development Status :: 5 - Production/Stable
Classifier: Environment :: Web Environment
Classifier: Framework :: Paste
Classifier: Framework :: Zope :: 3
Classifier: Intended Audience :: End Users/Desktop
Classifier: Intended Audience :: Information Technology
Classifier: Intended Audience :: Other Audience
Classifier: License :: OSI Approved :: MIT License
Classifier: Natural Language :: English
Classifier: Natural Language :: German
Classifier: Operating System :: OS Independent
Classifier: Programming Language :: Python :: 2
Classifier: Programming Language :: Python :: 2.7
Classifier: Programming Language :: Python :: 3
Classifier: Programming Language :: Python :: 3.8
Classifier: Programming Language :: Python :: Implementation :: CPython
Classifier: Topic :: Communications :: Email :: Address Book
Classifier: Topic :: Communications :: Telephony
Classifier: Topic :: Internet :: WWW/HTTP :: WSGI :: Application
Classifier: Topic :: Office/Business :: Groupware
Requires-Dist: ZConfig
Requires-Dist: ZEO
Requires-Dist: ZODB
Requires-Dist: collective.monkeypatcher
Requires-Dist: fanstatic
Requires-Dist: gocept.country
Requires-Dist: gocept.pagelet
Requires-Dist: gocept.reference
Requires-Dist: grokcore.component (>=2.5.1.dev1)
Requires-Dist: icalendar
Requires-Dist: icemac.ab.locales[compile] (>=2.25)
Requires-Dist: icemac.truncatetext
Requires-Dist: js.bootstrap4
Requires-Dist: js.cookieconsent
Requires-Dist: js.jquery
Requires-Dist: js.jquery-timepicker-addon
Requires-Dist: js.jqueryui
Requires-Dist: js.select2
Requires-Dist: setuptools
Requires-Dist: six
Requires-Dist: xlwt
Requires-Dist: z3c.authviewlet
Requires-Dist: z3c.flashmessage
Requires-Dist: z3c.form (>=3.3.1.dev0)
Requires-Dist: z3c.formui
Requires-Dist: z3c.layer.pagelet
Requires-Dist: z3c.locales[compile] (>=0.3.0)
Requires-Dist: z3c.menu.ready2go
Requires-Dist: z3c.pagelet
Requires-Dist: z3c.pagelet[chameleon]
Requires-Dist: z3c.preference (>=0.2)
Requires-Dist: z3c.ptcompat
Requires-Dist: z3c.table (>=2)
Requires-Dist: z3c.wizard
Requires-Dist: zc.catalog
Requires-Dist: zc.sourcefactory
Requires-Dist: zdaemon
Requires-Dist: zodbupdate
Requires-Dist: zope.schema (>=4.3zope.app.appsetup)
Requires-Dist: zope.app.locales (>=3.6)
Requires-Dist: zope.app.wsgi
Requires-Dist: zope.browserpage
Requires-Dist: zope.copypastemove
Requires-Dist: zope.generations
Requires-Dist: zope.globalrequest
Requires-Dist: zope.i18n[compile,zcml]
Requires-Dist: zope.interface
Requires-Dist: zope.login
Requires-Dist: zope.mimetype
Requires-Dist: zope.pluggableauth
Requires-Dist: zope.preference
Requires-Dist: zope.principalannotation
Requires-Dist: zope.principalregistry
Requires-Dist: zope.publisher
Requires-Dist: zope.securitypolicy (>=4.1)
Requires-Dist: zope.session
Requires-Dist: zope.traversing
Provides-Extra: docs
Requires-Dist: Sphinx ; extra == 'docs'
Requires-Dist: recommonmark ; extra == 'docs'
Provides-Extra: test
Requires-Dist: WebTest (>=2.0.25.dev0) ; extra == 'test'
Requires-Dist: beautifulsoup4 ; extra == 'test'
Requires-Dist: gocept.httpserverlayer ; extra == 'test'
Requires-Dist: gocept.jslint ; extra == 'test'
Requires-Dist: gocept.testing ; extra == 'test'
Requires-Dist: mock ; extra == 'test'
Requires-Dist: plone.testing ; extra == 'test'
Requires-Dist: pytest ; extra == 'test'
Requires-Dist: selenium (>=3) ; extra == 'test'
Requires-Dist: xlrd ; extra == 'test'
Requires-Dist: z3c.etestbrowser ; extra == 'test'
Requires-Dist: zc.buildout ; extra == 'test'
Requires-Dist: zope.testbrowser (>=5.2.3.dev0) ; extra == 'test'
Requires-Dist: zope.testing (>=3.8) ; extra == 'test'
